[
  {
    "name": "fandom-com",
    "isBig": false,
    "image": "https://vignette.wikia.nocookie.net/central/images/b/bc/Wiki.png/revision/latest?cb=20180423162614",
    "heading": "Ewan McGregor Returns as Obi-Wan Kenobi in Disney+ Series",
    "subheading": "Presented by Disney+",
    "link": "https://fandom.com",
    "isExternal": false,
    "priority": 3,
    "disableOnSearch": false,
    "disableOnPage": false,
    "onlyOnAndroid": false,
    "onlyOnIOS": false
  },
  {
    "name": "fandom-big",
    "isBig": true,
    "image": "https://vignette.wikia.nocookie.net/central/images/b/bc/Wiki.png/revision/latest?cb=20180423162614",
    "heading": "BIG Ewan McGregor Returns as Obi-Wan Kenobi in Disney+ Series",
    "subheading": "Presented by Disney+",
    "link": "https://fandom.com",
    "priority": 2
  },
  {
    "name": "xkxd02",
    "isBig": true,
    "image": "https://vignette.wikia.nocookie.net/central/images/b/bc/Wiki.png/revision/latest?cb=20190830144754",
    "heading": "BIG Ewan McGregor Returns as Obi-Wan Kenobi in Disney+ Series",
    "subheading": "Presented by Disney+",
    "link": "https://www.fandom.com",
    "isExternal": false,
    "priority": 1
  },
  {
    "name": "xkxd02-small",
    "image": "https://vignette.wikia.nocookie.net/central/images/b/bc/Wiki.png/revision/latest?cb=20190830144754",
    "heading": "Ewan McGregor Returns as Obi-Wan Kenobi in Disney+ Series",
    "subheading": "Presented by Disney+",
    "link": "https://www.fandom.com",
    "isExternal": false,
    "priority": 2
  }
]
