[
  {
    "campaign": [
      "fandom-test"
    ],
    "category": [
      "fandom-test"
    ],
    "wikiId": [
      1081891
    ],
    "query": [
      "coffee"
    ]
  },
  {
    "campaign": [
      "fandom-test"
    ],
    "category": [
      "fandom-test"
    ],
    "wikiId": [
      1081891
    ],
    "query": [
      "foo"
    ]
  },
  {
    "campaign": "fandom-test",
    "category": "fandom-test-search-big",
    "wikiId": [
      1575417,
      1619010
    ],
    "query": [
      "spiderman",
      "marvel",
      "test"
    ]
  },
  {
    "campaign": "fandom-test",
    "category": "fandom-test-search",
    "wikiId": [
      1575417,
      1619010
    ]
  }
]
